idiom/__init__.py
idiom/high_dimensional_stats.py
idiom/data/english-word-frequency.csv.zip
idiom-0.1.6.dist-info/LICENSE
idiom-0.1.6.dist-info/METADATA
idiom-0.1.6.dist-info/WHEEL
idiom-0.1.6.dist-info/top_level.txt
idiom-0.1.6.dist-info/RECORD
