Metadata-Version: 2.1
Name: idiom
Version: 0.1.6
Summary: Access and operations with word2vec data
Home-page: https://github.com/thorwhalen/idiom
Author: Thor Whalen
License: mit
Platform: any
License-File: LICENSE
Requires-Dist: numpy
Requires-Dist: scikit-learn
Requires-Dist: py2store
Requires-Dist: graze
Requires-Dist: creek
Requires-Dist: nltk
Requires-Dist: inflect
